myrepoutils/__init__.py
myrepoutils-0.1.4.dist-info/LICENSE
myrepoutils-0.1.4.dist-info/METADATA
myrepoutils-0.1.4.dist-info/WHEEL
myrepoutils-0.1.4.dist-info/RECORD
